pymemobird/__init__.py
pymemobird/__version__.py
pymemobird/device.py
pymemobird/paper.py
pymemobird/user.py
pymemobird/util.py
pymemobird-0.2.2.dist-info/LICENSE
pymemobird-0.2.2.dist-info/METADATA
pymemobird-0.2.2.dist-info/WHEEL
pymemobird-0.2.2.dist-info/top_level.txt
pymemobird-0.2.2.dist-info/RECORD
