Metadata-Version: 2.1
Name: pymemobird
Version: 0.2.2
Summary: Memobird咕咕机Python开发工具包，使用官方API，OOP风格。可打印文本和图片，支持中文（GBK）、PNG、JPG。
Home-page: https://github.com/wolfbolin/pymemobird
Author: WolfBolin
Author-email: mailto@wolfbolin.com
License: MIT
Platform: UNKNOWN
Classifier: License :: OSI Approved :: MIT License
Classifier: Programming Language :: Python
Classifier: Programming Language :: Python :: 3
Classifier: Programming Language :: Python :: 3.6
Classifier: Programming Language :: Python :: Implementation :: CPython
Classifier: Programming Language :: Python :: Implementation :: PyPy
Requires-Python: >=3.6.0
Requires-Dist: requests
Requires-Dist: requests (==2.21.0)
